[{"altitude": 545.6, "date": ["2020-10-16 10:41:45", "2020-10-16 10:41:45", "2020-10-16 10:41:45"], "m1": [7, 7, 6], "m2": [5, 5, 5], "m3": [7, 7, 7], "m4": [7, 7, 8], "position": [-33.46, -70.66], "pressure": 955.39, "temperature": 10.57, "unit": "001"}, {"altitude": 549.0, "date": ["2020-10-16 10:46:45", "2020-10-16 10:46:45", "2020-10-16 10:46:45"], "m1": [7, 7, 7], "m2": [5, 5, 5], "m3": [7, 7, 8], "m4": [7, 8, 8], "position": [-33.46, -70.66], "pressure": 955.37, "temperature": 10.7, "unit": "001"}, {"altitude": 565.6, "date": ["2020-10-16 10:51:45", "2020-10-16 10:51:45", "2020-10-16 10:51:45"], "m1": [7, 7, 7], "m2": [5, 5, 5], "m3": [7, 7, 7], "m4": [8, 8, 7], "position": [-33.46, -70.66], "pressure": 955.41, "temperature": 10.84, "unit": "001"}, {"altitude": 553.7, "date": ["2020-10-16 10:56:45", "2020-10-16 10:56:45", "2020-10-16 10:56:45"], "m1": [7, 7, 7], "m2": [5, 5, 5], "m3": [7, 7, 7], "m4": [7, 8, 8], "position": [-33.46, -70.66], "pressure": 955.44, "temperature": 11.06, "unit": "001"}, {"altitude": 554.7, "date": ["2020-10-16 11:01:45", "2020-10-16 11:01:45", "2020-10-16 11:01:45"], "m1": [7, 7, 7], "m2": [5, 5, 5], "m3": [7, 7, 7], "m4": [8, 8, 8], "position": [-33.46, -70.66], "pressure": 955.59, "temperature": 11.16, "unit": "001"}, {"altitude": 551.9, "date": ["2020-10-16 11:06:45", "2020-10-16 11:06:45", "2020-10-16 11:06:45"], "m1": [6, 7, 7], "m2": [5, 5, 5], "m3": [7, 8, 7], "m4": [8, 8, 7], "position": [-33.46, -70.66], "pressure": 955.75, "temperature": 11.38, "unit": "001"}, {"altitude": 552.4, "date": ["2020-10-16 11:11:45", "2020-10-16 11:11:45", "2020-10-16 11:11:45"], "m1": [7, 6, 6], "m2": [5, 5, 5], "m3": [7, 7, 7], "m4": [8, 8, 8], "position": [-33.46, -70.66], "pressure": 955.73, "temperature": 11.71, "unit": "001"}, {"altitude": 564.4, "date": ["2020-10-16 11:16:45", "2020-10-16 11:16:45", "2020-10-16 11:16:45"], "m1": [6, 7, 6], "m2": [5, 5, 5], "m3": [7, 7, 7], "m4": [8, 8, 8], "position": [-33.46, -70.66], "pressure": 955.87, "temperature": 11.82, "unit": "001"}, {"altitude": 545.9, "date": ["2020-10-16 11:21:45", "2020-10-16 11:21:45", "2020-10-16 11:21:45"], "m1": [6, 6, 6], "m2": [5, 5, 5], "m3": [6, 6, 7], "m4": [8, 7, 7], "position": [-33.46, -70.66], "pressure": 955.81, "temperature": 12.18, "unit": "001"}, {"altitude": 559.0, "date": ["2020-10-16 11:26:45", "2020-10-16 11:26:45", "2020-10-16 11:26:45"], "m1": [6, 6, 6], "m2": [5, 5, 5], "m3": [6, 6, 6], "m4": [7, 8, 8], "position": [-33.46, -70.66], "pressure": 955.87, "temperature": 12.45, "unit": "001"}, {"altitude": 558.2, "date": ["2020-10-16 11:31:45", "2020-10-16 11:31:45", "2020-10-16 11:31:45"], "m1": [6, 6, 6], "m2": [5, 5, 5], "m3": [5, 5, 5], "m4": [6, 6, 7], "position": [-33.46, -70.66], "pressure": 955.94, "temperature": 13.01, "unit": "001"}, {"altitude": 554.7, "date": ["2020-10-16 11:36:45", "2020-10-16 11:36:45", "2020-10-16 11:36:45"], "m1": [7, 6, 6], "m2": [5, 5, 5], "m3": [5, 5, 5], "m4": [6, 6, 6], "position": [-33.46, -70.66], "pressure": 955.98, "temperature": 12.94, "unit": "001"}, {"altitude": 551.5, "date": ["2020-10-16 11:41:45", "2020-10-16 11:41:45", "2020-10-16 11:41:45"], "m1": [6, 6, 6], "m2": [5, 5, 5], "m3": [5, 5, 5], "m4": [6, 6, 6], "position": [-33.46, -70.66], "pressure": 956.11, "temperature": 13.09, "unit": "001"}, {"altitude": 555.2, "date": ["2020-10-16 11:46:45", "2020-10-16 11:46:45", "2020-10-16 11:46:45"], "m1": [6, 6, 6], "m2": [5, 5, 5], "m3": [5, 5, 5], "m4": [6, 6, 6], "position": [-33.46, -70.66], "pressure": 956.14, "temperature": 13.47, "unit": "001"}, {"altitude": 560.4, "date": ["2020-10-16 11:51:45", "2020-10-16 11:51:45", "2020-10-16 11:51:45"], "m1": [6, 6, 6], "m2": [5, 5, 5], "m3": [5, 5, 5], "m4": [6, 6, 6], "position": [-33.46, -70.66], "pressure": 956.19, "temperature": 13.55, "unit": "001"}, {"altitude": 556.5, "date": ["2020-10-16 11:56:45", "2020-10-16 11:56:45", "2020-10-16 11:56:45"], "m1": [6, 6, 6], "m2": [5, 5, 5], "m3": [5, 5, 5], "m4": [6, 6, 6], "position": [-33.46, -70.66], "pressure": 956.25, "temperature": 13.72, "unit": "001"}, {"altitude": 555.7, "date": ["2020-10-16 12:01:45", "2020-10-16 12:01:45", "2020-10-16 12:01:45"], "m1": [6, 4095, 4095], "m2": [5, 4095, 3584], "m3": [5, 4095, 4095], "m4": [6, 4095, 4095], "position": [-33.46, -70.66], "pressure": 956.21, "temperature": 14.1, "unit": "001"}, {"altitude": 558.0, "date": ["2020-10-16 12:06:45", "2020-10-16 12:06:45", "2020-10-16 12:06:45"], "m1": [7, 4095, 544], "m2": [5, 4095, 5], "m3": [5, 4095, 2048], "m4": [6, 4095, 6], "position": [-33.46, -70.66], "pressure": 956.28, "temperature": 15.07, "unit": "001"}, {"altitude": 554.6, "date": ["2020-10-16 12:11:45", "2020-10-16 12:11:45", "2020-10-16 12:11:45"], "m1": [1088, 4095, 4095], "m2": [5, 4095, 4095], "m3": [512, 4095, 4095], "m4": [6, 4095, 3968], "position": [-33.46, -70.66], "pressure": 956.44, "temperature": 15.6, "unit": "001"}, {"altitude": 559.1, "date": ["2020-10-16 12:16:45", "2020-10-16 12:16:45", "2020-10-16 12:16:45"], "m1": [4095, 4095, 2176], "m2": [4095, 4095, 7], "m3": [4095, 2752, 3072], "m4": [4095, 4095, 7], "position": [-33.46, -70.66], "pressure": 956.46, "temperature": 16.5, "unit": "001"}, {"altitude": 574.7, "date": ["2020-10-16 12:21:45", "2020-10-16 12:21:45", "2020-10-16 12:21:45"], "m1": [4095, 7, 0], "m2": [47, 5, 0], "m3": [1088, 5, 0], "m4": [54, 5, 0], "position": [-33.46, -70.66], "pressure": 956.43, "temperature": 16.62, "unit": "001"}, {"altitude": 564.9, "date": ["2020-10-16 12:26:45", "2020-10-16 12:26:45", "2020-10-16 12:26:45"], "m1": [4095, 7, 0], "m2": [4095, 5, 0], "m3": [4095, 5, 0], "m4": [4095, 4, 0], "position": [-33.46, -70.66], "pressure": 956.48, "temperature": 17.41, "unit": "001"}, {"altitude": 566.7, "date": ["2020-10-16 12:31:45", "2020-10-16 12:31:45", "2020-10-16 12:31:45"], "m1": [8, 0, 0], "m2": [6, 0, 0], "m3": [1088, 0, 0], "m4": [6, 0, 0], "position": [-33.46, -70.66], "pressure": 956.45, "temperature": 18.1, "unit": "001"}, {"altitude": 584.9, "date": ["2020-10-16 12:36:45", "2020-10-16 12:36:45", "2020-10-16 12:36:45"], "m1": [0, 0, 0], "m2": [5, 0, 0], "m3": [68, 0, 0], "m4": [0, 0, 0], "position": [-33.46, -70.66], "pressure": 956.49, "temperature": 19.01, "unit": "001"}, {"altitude": 574.5, "date": ["2020-10-16 12:41:45", "2020-10-16 12:41:45", "2020-10-16 12:41:45"], "m1": [4095, 0, 0], "m2": [4095, 0, 0], "m3": [4095, 0, 0], "m4": [4095, 0, 0], "position": [-33.46, -70.66], "pressure": 956.27, "temperature": 19.67, "unit": "001"}, {"altitude": 561.1, "date": ["2020-10-16 12:46:45", "2020-10-16 12:46:45", "2020-10-16 12:46:45"], "m1": [4095, 0, 0], "m2": [4095, 0, 0], "m3": [4095, 0, 0], "m4": [4095, 0, 0], "position": [-33.46, -70.66], "pressure": 956.36, "temperature": 20.31, "unit": "001"}, {"altitude": 565.3, "date": ["2020-10-16 12:51:45", "2020-10-16 12:51:45", "2020-10-16 12:51:45"], "m1": [4095, 0, 0], "m2": [4095, 0, 0], "m3": [4095, 0, 0], "m4": [4095, 0, 0], "position": [-33.46, -70.66], "pressure": 956.3, "temperature": 21.18, "unit": "001"}, {"altitude": 557.5, "date": ["2020-10-16 12:56:45", "2020-10-16 12:56:45", "2020-10-16 12:56:45"], "m1": [4095, 0, 0], "m2": [4095, 0, 0], "m3": [4095, 0, 0], "m4": [4095, 0, 0], "position": [-33.46, -70.66], "pressure": 956.19, "temperature": 22.0, "unit": "001"}, {"altitude": 553.3, "date": ["2020-10-16 13:01:45", "2020-10-16 13:01:45", "2020-10-16 13:01:45"], "m1": [4095, 0, 0], "m2": [4095, 0, 0], "m3": [4095, 0, 0], "m4": [4095, 0, 0], "position": [-33.46, -70.66], "pressure": 956.1, "temperature": 22.83, "unit": "001"}, {"altitude": 567.4, "date": ["2020-10-16 13:06:45", "2020-10-16 13:06:45", "2020-10-16 13:06:45"], "m1": [4095, 0, 0], "m2": [4095, 0, 0], "m3": [4095, 0, 0], "m4": [4095, 0, 0], "position": [-33.46, -70.66], "pressure": 956.11, "temperature": 23.46, "unit": "001"}, {"altitude": 559.0, "date": ["2020-10-16 13:11:45", "2020-10-16 13:11:45", "2020-10-16 13:11:45"], "m1": [4095, 0, 0], "m2": [4095, 0, 0], "m3": [4095, 0, 0], "m4": [4095, 0, 0], "position": [-33.46, -70.66], "pressure": 956.12, "temperature": 24.66, "unit": "001"}, {"altitude": 564.5, "date": ["2020-10-16 13:16:45", "2020-10-16 13:16:45", "2020-10-16 13:16:45"], "m1": [4095, 0, 0], "m2": [4095, 0, 0], "m3": [4095, 0, 0], "m4": [4095, 0, 0], "position": [-33.46, -70.66], "pressure": 956.08, "temperature": 24.89, "unit": "001"}, {"altitude": 549.8, "date": ["2020-10-16 13:21:45", "2020-10-16 13:21:45", "2020-10-16 13:21:45"], "m1": [4095, 0, 0], "m2": [4095, 0, 0], "m3": [4095, 0, 0], "m4": [4095, 0, 0], "position": [-33.46, -70.66], "pressure": 956.07, "temperature": 25.5, "unit": "001"}, {"altitude": 552.0, "date": ["2020-10-16 13:26:45", "2020-10-16 13:26:45", "2020-10-16 13:26:45"], "m1": [4095, 0, 4095], "m2": [4095, 0, 4095], "m3": [4095, 0, 4095], "m4": [4095, 0, 4095], "position": [-33.46, -70.66], "pressure": 956.11, "temperature": 25.98, "unit": "001"}, {"altitude": 554.3, "date": ["2020-10-16 13:31:45", "2020-10-16 13:31:45", "2020-10-16 13:31:45"], "m1": [4095, 0, 0], "m2": [4095, 0, 0], "m3": [4095, 0, 0], "m4": [4095, 0, 0], "position": [-33.46, -70.66], "pressure": 956.19, "temperature": 26.13, "unit": "001"}, {"altitude": 565.4, "date": ["2020-10-16 13:36:45", "2020-10-16 13:36:45", "2020-10-16 13:36:45"], "m1": [4095, 672, 0], "m2": [4095, 5, 0], "m3": [4095, 2048, 0], "m4": [4095, 6, 0], "position": [-33.46, -70.66], "pressure": 956.18, "temperature": 26.39, "unit": "001"}, {"altitude": 571.9, "date": ["2020-10-16 13:41:45", "2020-10-16 13:41:45", "2020-10-16 13:41:45"], "m1": [4095, 0, 0], "m2": [4095, 0, 0], "m3": [4095, 0, 0], "m4": [4095, 0, 0], "position": [-33.46, -70.66], "pressure": 956.17, "temperature": 26.18, "unit": "001"}, {"altitude": 556.6, "date": ["2020-10-16 13:46:45", "2020-10-16 13:46:45", "2020-10-16 13:46:45"], "m1": [4095, 0, 0], "m2": [4095, 0, 0], "m3": [4095, 0, 0], "m4": [4095, 0, 0], "position": [-33.46, -70.66], "pressure": 956.31, "temperature": 27.14, "unit": "001"}, {"altitude": 553.4, "date": ["2020-10-16 13:51:45", "2020-10-16 13:51:45", "2020-10-16 13:51:45"], "m1": [4095, 0, 0], "m2": [4095, 0, 0], "m3": [4095, 0, 0], "m4": [4095, 0, 0], "position": [-33.46, -70.66], "pressure": 956.26, "temperature": 27.45, "unit": "001"}, {"altitude": 564.1, "date": ["2020-10-16 13:56:45", "2020-10-16 13:56:45", "2020-10-16 13:56:45"], "m1": [4095, 0, 0], "m2": [4095, 0, 0], "m3": [4095, 0, 0], "m4": [4095, 0, 0], "position": [-33.46, -70.66], "pressure": 956.32, "temperature": 27.06, "unit": "001"}, {"altitude": 571.0, "date": ["2020-10-16 14:01:45", "2020-10-16 14:01:45", "2020-10-16 14:01:45"], "m1": [4095, 0, 0], "m2": [4095, 0, 0], "m3": [4095, 0, 0], "m4": [4095, 0, 0], "position": [-33.46, -70.66], "pressure": 956.31, "temperature": 27.04, "unit": "001"}, {"altitude": 564.9, "date": ["2020-10-16 14:06:45", "2020-10-16 14:06:45", "2020-10-16 14:06:45"], "m1": [4095, 0, 0], "m2": [4095, 0, 0], "m3": [4095, 0, 0], "m4": [4095, 0, 0], "position": [-33.46, -70.66], "pressure": 956.29, "temperature": 27.56, "unit": "001"}, {"altitude": 562.1, "date": ["2020-10-16 14:11:45", "2020-10-16 14:11:45", "2020-10-16 14:11:45"], "m1": [4095, 0, 0], "m2": [4095, 0, 0], "m3": [4095, 0, 0], "m4": [4095, 0, 0], "position": [-33.46, -70.66], "pressure": 956.37, "temperature": 27.17, "unit": "001"}, {"altitude": 579.6, "date": ["2020-10-16 14:16:45", "2020-10-16 14:16:45", "2020-10-16 14:16:45"], "m1": [4095, 0, 0], "m2": [4095, 0, 0], "m3": [4095, 0, 0], "m4": [4095, 0, 0], "position": [-33.46, -70.66], "pressure": 956.4, "temperature": 27.2, "unit": "001"}, {"altitude": 576.8, "date": ["2020-10-16 14:21:45", "2020-10-16 14:21:45", "2020-10-16 14:21:45"], "m1": [4095, 4095, 4095], "m2": [4095, 4095, 4095], "m3": [4095, 4095, 4079], "m4": [4095, 2047, 2047], "position": [-33.46, -70.66], "pressure": 956.43, "temperature": 27.64, "unit": "001"}, {"altitude": 560.1, "date": ["2020-10-16 14:26:45", "2020-10-16 14:26:45", "2020-10-16 14:26:45"], "m1": [4095, 0, 0], "m2": [4095, 0, 0], "m3": [4095, 0, 0], "m4": [4095, 0, 0], "position": [-33.46, -70.66], "pressure": 956.5, "temperature": 28.3, "unit": "001"}, {"altitude": 558.1, "date": ["2020-10-16 14:31:45", "2020-10-16 14:31:45", "2020-10-16 14:31:45"], "m1": [4095, 0, 0], "m2": [4095, 0, 0], "m3": [4095, 0, 0], "m4": [4095, 0, 0], "position": [-33.46, -70.66], "pressure": 956.4, "temperature": 29.1, "unit": "001"}, {"altitude": 555.4, "date": ["2020-10-16 14:36:45", "2020-10-16 14:36:45", "2020-10-16 14:36:45"], "m1": [4095, 0, 0], "m2": [4095, 0, 0], "m3": [4095, 0, 0], "m4": [4095, 0, 0], "position": [-33.46, -70.66], "pressure": 956.44, "temperature": 29.38, "unit": "001"}, {"altitude": 559.2, "date": ["2020-10-16 14:41:45", "2020-10-16 14:41:45", "2020-10-16 14:41:45"], "m1": [4095, 0, 0], "m2": [4095, 0, 0], "m3": [4095, 0, 0], "m4": [4095, 0, 0], "position": [-33.46, -70.66], "pressure": 956.53, "temperature": 28.96, "unit": "001"}, {"altitude": 551.8, "date": ["2020-10-16 14:46:45", "2020-10-16 14:46:45", "2020-10-16 14:46:45"], "m1": [4095, 0, 0], "m2": [4095, 0, 0], "m3": [4095, 0, 0], "m4": [4095, 0, 0], "position": [-33.46, -70.66], "pressure": 956.55, "temperature": 28.27, "unit": "001"}, {"altitude": 548.1, "date": ["2020-10-16 14:51:45", "2020-10-16 14:51:45", "2020-10-16 14:51:45"], "m1": [4095, 0, 0], "m2": [4095, 0, 0], "m3": [4095, 0, 0], "m4": [4095, 0, 0], "position": [-33.46, -70.66], "pressure": 956.66, "temperature": 28.36, "unit": "001"}, {"altitude": 559.6, "date": ["2020-10-16 14:56:45", "2020-10-16 14:56:45", "2020-10-16 14:56:45"], "m1": [4095, 0, 0], "m2": [4095, 0, 0], "m3": [4095, 0, 0], "m4": [4095, 0, 0], "position": [-33.46, -70.66], "pressure": 956.6, "temperature": 28.27, "unit": "001"}, {"altitude": 556.0, "date": ["2020-10-16 15:01:45", "2020-10-16 15:01:45", "2020-10-16 15:01:45"], "m1": [4095, 0, 0], "m2": [4095, 0, 0], "m3": [4095, 0, 0], "m4": [4095, 0, 0], "position": [-33.46, -70.66], "pressure": 956.65, "temperature": 28.21, "unit": "001"}, {"altitude": 556.0, "date": ["2020-10-16 15:02:22", "2020-10-16 15:02:22", "2020-10-16 15:02:22"], "m1": [4095, 0, 0], "m2": [4095, 0, 0], "m3": [4095, 0, 0], "m4": [4095, 0, 0], "position": [-33.46, -70.66], "pressure": 956.65, "temperature": 28.26, "unit": "001"}, {"altitude": 557.8, "date": ["2020-10-16 15:06:45", "2020-10-16 15:06:45", "2020-10-16 15:06:45"], "m1": [4095, 0, 0], "m2": [4095, 0, 0], "m3": [4095, 0, 0], "m4": [4095, 0, 0], "position": [-33.46, -70.66], "pressure": 956.63, "temperature": 28.44, "unit": "001"}, {"altitude": 560.1, "date": ["2020-10-16 15:11:45", "2020-10-16 15:11:45", "2020-10-16 15:11:45"], "m1": [4095, 0, 0], "m2": [4095, 0, 0], "m3": [4095, 0, 0], "m4": [4095, 0, 0], "position": [-33.46, -70.66], "pressure": 956.59, "temperature": 29.16, "unit": "001"}, {"altitude": 554.9, "date": ["2020-10-16 15:16:45", "2020-10-16 15:16:45", "2020-10-16 15:16:45"], "m1": [4095, 0, 0], "m2": [4095, 0, 0], "m3": [4095, 0, 0], "m4": [4095, 0, 0], "position": [-33.46, -70.66], "pressure": 956.57, "temperature": 28.45, "unit": "001"}, {"altitude": 554.3, "date": ["2020-10-16 15:21:45", "2020-10-16 15:21:45", "2020-10-16 15:21:45"], "m1": [4095, 0, 0], "m2": [4095, 0, 0], "m3": [4095, 0, 0], "m4": [4095, 0, 0], "position": [-33.46, -70.66], "pressure": 956.49, "temperature": 28.78, "unit": "001"}, {"altitude": 579.9, "date": ["2020-10-16 15:26:45", "2020-10-16 15:26:45", "2020-10-16 15:26:45"], "m1": [4095, 2816, 2976], "m2": [4095, 3968, 2048], "m3": [4095, 3078, 3968], "m4": [4095, 2048, 1676], "position": [-33.46, -70.66], "pressure": 956.49, "temperature": 27.58, "unit": "001"}, {"altitude": 577.7, "date": ["2020-10-16 15:31:45", "2020-10-16 15:31:45", "2020-10-16 15:31:45"], "m1": [1344, 4092, 3968], "m2": [752, 4095, 568], "m3": [3072, 3584, 3072], "m4": [1219, 63, 841], "position": [-33.46, -70.66], "pressure": 956.4, "temperature": 27.51, "unit": "001"}, {"altitude": 559.9, "date": ["2020-10-16 15:36:45", "2020-10-16 15:36:45", "2020-10-16 15:36:45"], "m1": [1366, 4095, 2560], "m2": [1248, 4095, 4095], "m3": [1258, 4095, 4095], "m4": [1567, 4095, 4064], "position": [-33.46, -70.66], "pressure": 956.42, "temperature": 28.95, "unit": "001"}, {"altitude": 552.1, "date": ["2020-10-16 15:41:45", "2020-10-16 15:41:45", "2020-10-16 15:41:45"], "m1": [1328, 681, 830], "m2": [1267, 877, 966], "m3": [1235, 674, 913], "m4": [1638, 1385, 1504], "position": [-33.46, -70.66], "pressure": 956.38, "temperature": 29.96, "unit": "001"}, {"altitude": 553.4, "date": ["2020-10-16 15:46:45", "2020-10-16 15:46:45", "2020-10-16 15:46:45"], "m1": [947, 1109, 1319], "m2": [900, 975, 1169], "m3": [764, 1006, 1196], "m4": [1356, 1456, 1715], "position": [-33.46, -70.66], "pressure": 956.33, "temperature": 30.58, "unit": "001"}, {"altitude": 551.0, "date": ["2020-10-16 15:51:45", "2020-10-16 15:51:45", "2020-10-16 15:51:45"], "m1": [1007, 1159, 1313], "m2": [1036, 1191, 1206], "m3": [828, 1008, 1226], "m4": [1571, 1612, 1630], "position": [-33.46, -70.66], "pressure": 956.32, "temperature": 31.32, "unit": "001"}, {"altitude": 550.9, "date": ["2020-10-16 15:56:45", "2020-10-16 15:56:45", "2020-10-16 15:56:45"], "m1": [1315, 1395, 1385], "m2": [1194, 1255, 1114], "m3": [1206, 1241, 1155], "m4": [1608, 1628, 1447], "position": [-33.46, -70.66], "pressure": 956.2, "temperature": 31.61, "unit": "001"}, {"altitude": 545.9, "date": ["2020-10-16 16:01:45", "2020-10-16 16:01:45", "2020-10-16 16:01:45"], "m1": [900, 413, 1222], "m2": [762, 596, 854], "m3": [739, 362, 1087], "m4": [1123, 966, 1255], "position": [-33.46, -70.66], "pressure": 956.17, "temperature": 31.44, "unit": "001"}, {"altitude": 553.1, "date": ["2020-10-16 16:06:45", "2020-10-16 16:06:45", "2020-10-16 16:06:45"], "m1": [76, 122, 102], "m2": [79, 131, 99], "m3": [66, 116, 93], "m4": [172, 185, 182], "position": [-33.46, -70.66], "pressure": 956.1, "temperature": 30.31, "unit": "001"}, {"altitude": 553.9, "date": ["2020-10-16 16:11:45", "2020-10-16 16:11:45", "2020-10-16 16:11:45"], "m1": [7, 7, 7], "m2": [6, 6, 6], "m3": [6, 7, 6], "m4": [7, 7, 7], "position": [-33.46, -70.66], "pressure": 956.2, "temperature": 27.59, "unit": "001"}, {"altitude": 553.1, "date": ["2020-10-16 16:16:45", "2020-10-16 16:16:45", "2020-10-16 16:16:45"], "m1": [259, 107, 124], "m2": [238, 118, 131], "m3": [211, 103, 109], "m4": [325, 165, 212], "position": [-33.46, -70.66], "pressure": 956.19, "temperature": 26.87, "unit": "001"}, {"altitude": 555.1, "date": ["2020-10-16 16:21:45", "2020-10-16 16:21:45", "2020-10-16 16:21:45"], "m1": [573, 602, 580], "m2": [469, 503, 563], "m3": [572, 407, 548], "m4": [649, 757, 771], "position": [-33.46, -70.66], "pressure": 956.22, "temperature": 27.36, "unit": "001"}, {"altitude": 553.6, "date": ["2020-10-16 16:26:45", "2020-10-16 16:26:45", "2020-10-16 16:26:45"], "m1": [174, 97, 158], "m2": [159, 112, 145], "m3": [152, 88, 112], "m4": [190, 171, 190], "position": [-33.46, -70.66], "pressure": 956.0, "temperature": 27.95, "unit": "001"}, {"altitude": 547.0, "date": ["2020-10-16 16:31:45", "2020-10-16 16:31:45", "2020-10-16 16:31:45"], "m1": [634, 1180, 1283], "m2": [759, 1051, 1151], "m3": [620, 1078, 1177], "m4": [1121, 1372, 1561], "position": [-33.46, -70.66], "pressure": 955.98, "temperature": 28.22, "unit": "001"}, {"altitude": 553.4, "date": ["2020-10-16 16:36:45", "2020-10-16 16:36:45", "2020-10-16 16:36:45"], "m1": [1057, 1097, 614], "m2": [1139, 761, 782], "m3": [1046, 964, 493], "m4": [1632, 1139, 1356], "position": [-33.46, -70.66], "pressure": 955.99, "temperature": 31.07, "unit": "001"}, {"altitude": 553.3, "date": ["2020-10-16 17:39:17", "2020-10-16 17:39:17", "2020-10-16 17:39:17"], "m1": [725, 140, 81], "m2": [638, 195, 56], "m3": [659, 99, 48], "m4": [792, 192, 35], "position": [-33.46, -70.66], "pressure": 955.38, "temperature": 34.04, "unit": "001"}, {"altitude": 546.1, "date": ["2020-10-16 17:53:48", "2020-10-16 17:53:48", "2020-10-16 17:53:48"], "m1": [309, 37, 732], "m2": [273, 27, 765], "m3": [223, 25, 602], "m4": [315, 18, 1165], "position": [-33.46, -70.66], "pressure": 955.42, "temperature": 32.69, "unit": "001"}, {"altitude": 552.2, "date": ["2020-10-16 18:01:45", "2020-10-16 18:01:45", "2020-10-16 18:01:45"], "m1": [1043, 227, 441], "m2": [1061, 339, 671], "m3": [1068, 240, 349], "m4": [1475, 572, 1092], "position": [-33.46, -70.66], "pressure": 955.46, "temperature": 32.53, "unit": "001"}, {"altitude": 547.0, "date": ["2020-10-16 18:06:45", "2020-10-16 18:06:45", "2020-10-16 18:06:45"], "m1": [888, 1136, 644], "m2": [693, 837, 613], "m3": [783, 863, 465], "m4": [1122, 1164, 825], "position": [-33.46, -70.66], "pressure": 955.39, "temperature": 32.57, "unit": "001"}, {"altitude": 544.3, "date": ["2020-10-16 18:11:45", "2020-10-16 18:11:45", "2020-10-16 18:11:45"], "m1": [1142, 69, 1395], "m2": [1040, 106, 1251], "m3": [1087, 71, 1164], "m4": [1620, 160, 1672], "position": [-33.46, -70.66], "pressure": 955.43, "temperature": 33.82, "unit": "001"}, {"altitude": 546.5, "date": ["2020-10-16 18:16:45", "2020-10-16 18:16:45", "2020-10-16 18:16:45"], "m1": [97, 1374, 454], "m2": [66, 1020, 655], "m3": [60, 1241, 358], "m4": [25, 1615, 1207], "position": [-33.46, -70.66], "pressure": 955.5, "temperature": 33.76, "unit": "001"}, {"altitude": 546.0, "date": ["2020-10-16 18:21:45", "2020-10-16 18:21:45", "2020-10-16 18:21:45"], "m1": [777, 121, 1156], "m2": [635, 136, 1212], "m3": [595, 110, 1200], "m4": [1193, 209, 1668], "position": [-33.46, -70.66], "pressure": 955.47, "temperature": 33.44, "unit": "001"}, {"altitude": 538.3, "date": ["2020-10-16 19:12:04", "2020-10-16 19:12:04", "2020-10-16 19:12:04"], "m1": [24, 14, 303], "m2": [14, 10, 444], "m3": [14, 11, 281], "m4": [21, 9, 595], "position": [-33.46, -70.66], "pressure": 954.93, "temperature": 30.68, "unit": "001"}, {"altitude": 548.5, "date": ["2020-10-16 19:21:45", "2020-10-16 19:21:45", "2020-10-16 19:21:45"], "m1": [221, 462, 396], "m2": [297, 529, 477], "m3": [157, 386, 419], "m4": [527, 847, 689], "position": [-33.46, -70.66], "pressure": 954.94, "temperature": 30.75, "unit": "001"}, {"altitude": 554.5, "date": ["2020-10-16 19:26:45", "2020-10-16 19:26:45", "2020-10-16 19:26:45"], "m1": [1044, 556, 352], "m2": [903, 683, 474], "m3": [912, 566, 290], "m4": [1183, 984, 636], "position": [-33.46, -70.66], "pressure": 954.86, "temperature": 30.6, "unit": "001"}, {"altitude": 556.5, "date": ["2020-10-16 19:31:45", "2020-10-16 19:31:45", "2020-10-16 19:31:45"], "m1": [17, 841, 239], "m2": [16, 928, 334], "m3": [11, 912, 164], "m4": [9, 1318, 419], "position": [-33.46, -70.66], "pressure": 954.92, "temperature": 31.37, "unit": "001"}, {"altitude": 552.5, "date": ["2020-10-16 19:36:45", "2020-10-16 19:36:45", "2020-10-16 19:36:45"], "m1": [396, 2688, 4095], "m2": [554, 4095, 4095], "m3": [279, 3328, 4095], "m4": [984, 526, 4095], "position": [-33.46, -70.66], "pressure": 955.01, "temperature": 31.9, "unit": "001"}, {"altitude": 553.2, "date": ["2020-10-16 19:46:45", "2020-10-16 19:46:45", "2020-10-16 19:46:45"], "m1": [4095, 2688, 0], "m2": [4095, 3840, 0], "m3": [4095, 2688, 0], "m4": [4095, 3072, 0], "position": [-33.46, -70.66], "pressure": 954.97, "temperature": 31.47, "unit": "001"}, {"altitude": 557.5, "date": ["2020-10-16 19:56:45", "2020-10-16 19:56:45", "2020-10-16 19:56:45"], "m1": [3072, 0, 0], "m2": [4095, 0, 0], "m3": [3072, 0, 0], "m4": [9, 0, 0], "position": [-33.46, -70.66], "pressure": 955.06, "temperature": 31.01, "unit": "001"}, {"altitude": 552.7, "date": ["2020-10-16 20:06:45", "2020-10-16 20:06:45", "2020-10-16 20:06:45"], "m1": [4095, 999, 17], "m2": [4095, 918, 11], "m3": [4095, 783, 11], "m4": [4095, 1242, 9], "position": [-33.46, -70.66], "pressure": 954.94, "temperature": 30.48, "unit": "001"}, {"altitude": 548.8, "date": ["2020-10-16 20:11:45", "2020-10-16 20:11:45", "2020-10-16 20:11:45"], "m1": [4095, 0, 0], "m2": [4095, 0, 0], "m3": [4095, 0, 0], "m4": [4095, 0, 0], "position": [-33.46, -70.66], "pressure": 955.03, "temperature": 30.57, "unit": "001"}, {"altitude": 559.5, "date": ["2020-10-16 20:21:45", "2020-10-16 20:21:45", "2020-10-16 20:21:45"], "m1": [4095, 0, 0], "m2": [4095, 0, 0], "m3": [4095, 0, 0], "m4": [4095, 0, 0], "position": [-33.46, -70.66], "pressure": 954.95, "temperature": 31.56, "unit": "001"}, {"altitude": 555.4, "date": ["2020-10-16 20:26:45", "2020-10-16 20:26:45", "2020-10-16 20:26:45"], "m1": [4095, 0, 0], "m2": [4095, 0, 0], "m3": [4095, 0, 0], "m4": [4095, 0, 0], "position": [-33.46, -70.66], "pressure": 954.97, "temperature": 31.36, "unit": "001"}, {"altitude": 570.9, "date": ["2020-10-16 20:31:45", "2020-10-16 20:31:45", "2020-10-16 20:31:45"], "m1": [4095, 0, 0], "m2": [4095, 0, 0], "m3": [4095, 0, 0], "m4": [4095, 0, 0], "position": [-33.46, -70.66], "pressure": 954.97, "temperature": 31.13, "unit": "001"}, {"altitude": 553.4, "date": ["2020-10-16 20:36:45", "2020-10-16 20:36:45", "2020-10-16 20:36:45"], "m1": [4095, 0, 0], "m2": [4095, 0, 0], "m3": [4095, 0, 0], "m4": [4095, 0, 0], "position": [-33.46, -70.66], "pressure": 954.96, "temperature": 31.23, "unit": "001"}, {"altitude": 551.6, "date": ["2020-10-16 20:41:45", "2020-10-16 20:41:45", "2020-10-16 20:41:45"], "m1": [4095, 0, 0], "m2": [4095, 0, 0], "m3": [4095, 0, 0], "m4": [4095, 0, 0], "position": [-33.46, -70.66], "pressure": 954.9, "temperature": 30.88, "unit": "001"}, {"altitude": 554.7, "date": ["2020-10-16 20:46:45", "2020-10-16 20:46:45", "2020-10-16 20:46:45"], "m1": [4095, 0, 0], "m2": [4095, 0, 0], "m3": [4095, 0, 0], "m4": [4095, 0, 0], "position": [-33.46, -70.66], "pressure": 954.88, "temperature": 30.78, "unit": "001"}, {"altitude": 547.4, "date": ["2020-10-16 20:51:45", "2020-10-16 20:51:45", "2020-10-16 20:51:45"], "m1": [4095, 0, 0], "m2": [4095, 0, 0], "m3": [4095, 0, 0], "m4": [4095, 0, 0], "position": [-33.46, -70.66], "pressure": 954.83, "temperature": 30.95, "unit": "001"}, {"altitude": 553.8, "date": ["2020-10-16 20:56:45", "2020-10-16 20:56:45", "2020-10-16 20:56:45"], "m1": [4095, 0, 0], "m2": [4095, 0, 0], "m3": [4095, 0, 0], "m4": [4095, 0, 0], "position": [-33.46, -70.66], "pressure": 954.85, "temperature": 30.34, "unit": "001"}, {"altitude": 546.9, "date": ["2020-10-16 21:01:45", "2020-10-16 21:01:45", "2020-10-16 21:01:45"], "m1": [4095, 0, 0], "m2": [4095, 0, 0], "m3": [4095, 0, 0], "m4": [4095, 0, 0], "position": [-33.46, -70.66], "pressure": 954.75, "temperature": 29.43, "unit": "001"}, {"altitude": 547.9, "date": ["2020-10-16 21:06:45", "2020-10-16 21:06:45", "2020-10-16 21:06:45"], "m1": [4095, 0, 0], "m2": [4095, 0, 0], "m3": [4095, 0, 0], "m4": [4095, 0, 0], "position": [-33.46, -70.66], "pressure": 954.78, "temperature": 29.05, "unit": "001"}, {"altitude": 542.0, "date": ["2020-10-16 21:11:45", "2020-10-16 21:11:45", "2020-10-16 21:11:45"], "m1": [4095, 0, 0], "m2": [4095, 0, 0], "m3": [4095, 0, 0], "m4": [4095, 0, 0], "position": [-33.46, -70.66], "pressure": 954.91, "temperature": 28.85, "unit": "001"}, {"altitude": 542.1, "date": ["2020-10-16 21:16:45", "2020-10-16 21:16:45", "2020-10-16 21:16:45"], "m1": [4095, 0, 0], "m2": [4095, 0, 0], "m3": [4095, 0, 0], "m4": [4095, 0, 0], "position": [-33.46, -70.66], "pressure": 954.92, "temperature": 28.28, "unit": "001"}, {"altitude": 542.2, "date": ["2020-10-16 21:21:45", "2020-10-16 21:21:45", "2020-10-16 21:21:45"], "m1": [4095, 0, 0], "m2": [4095, 0, 0], "m3": [4095, 0, 0], "m4": [4095, 0, 0], "position": [-33.46, -70.66], "pressure": 954.85, "temperature": 28.03, "unit": "001"}, {"altitude": 547.5, "date": ["2020-10-16 21:26:45", "2020-10-16 21:26:45", "2020-10-16 21:26:45"], "m1": [4095, 0, 0], "m2": [4095, 0, 0], "m3": [4095, 0, 0], "m4": [4095, 0, 0], "position": [-33.46, -70.66], "pressure": 954.75, "temperature": 27.72, "unit": "001"}, {"altitude": 544.6, "date": ["2020-10-16 21:31:45", "2020-10-16 21:31:45", "2020-10-16 21:31:45"], "m1": [2816, 4095, 4095], "m2": [298, 4095, 4095], "m3": [512, 4095, 4095], "m4": [385, 3584, 4095], "position": [-33.46, -70.66], "pressure": 954.67, "temperature": 27.71, "unit": "001"}, {"altitude": 544.4, "date": ["2020-10-16 21:36:45", "2020-10-16 21:36:45", "2020-10-16 21:36:45"], "m1": [179, 221, 143], "m2": [216, 280, 185], "m3": [113, 226, 119], "m4": [417, 360, 234], "position": [-33.46, -70.66], "pressure": 954.77, "temperature": 27.57, "unit": "001"}, {"altitude": 547.5, "date": ["2020-10-16 21:41:45", "2020-10-16 21:41:45", "2020-10-16 21:41:45"], "m1": [138, 129, 51], "m2": [202, 200, 123], "m3": [101, 109, 40], "m4": [349, 310, 115], "position": [-33.46, -70.66], "pressure": 954.74, "temperature": 27.16, "unit": "001"}, {"altitude": 552.0, "date": ["2020-10-16 21:46:45", "2020-10-16 21:46:45", "2020-10-16 21:46:45"], "m1": [350, 253, 327], "m2": [306, 208, 279], "m3": [323, 208, 262], "m4": [337, 279, 340], "position": [-33.46, -70.66], "pressure": 954.78, "temperature": 26.9, "unit": "001"}, {"altitude": 555.0, "date": ["2020-10-16 21:51:45", "2020-10-16 21:51:45", "2020-10-16 21:51:45"], "m1": [144, 45, 203], "m2": [131, 93, 153], "m3": [99, 57, 160], "m4": [108, 157, 151], "position": [-33.46, -70.66], "pressure": 954.82, "temperature": 26.56, "unit": "001"}, {"altitude": 546.8, "date": ["2020-10-16 21:56:45", "2020-10-16 21:56:45", "2020-10-16 21:56:45"], "m1": [208, 155, 149], "m2": [238, 142, 163], "m3": [215, 115, 137], "m4": [252, 234, 231], "position": [-33.46, -70.66], "pressure": 954.88, "temperature": 25.97, "unit": "001"}, {"altitude": 555.4, "date": ["2020-10-16 22:01:45", "2020-10-16 22:01:45", "2020-10-16 22:01:45"], "m1": [77, 65, 168], "m2": [103, 82, 187], "m3": [60, 45, 179], "m4": [184, 173, 180], "position": [-33.46, -70.66], "pressure": 954.92, "temperature": 25.64, "unit": "001"}, {"altitude": 547.0, "date": ["2020-10-16 22:06:45", "2020-10-16 22:06:45", "2020-10-16 22:06:45"], "m1": [25, 15, 20], "m2": [31, 10, 18], "m3": [27, 11, 21], "m4": [57, 15, 28], "position": [-33.46, -70.66], "pressure": 955.01, "temperature": 25.03, "unit": "001"}, {"altitude": 552.4, "date": ["2020-10-16 22:11:45", "2020-10-16 22:11:45", "2020-10-16 22:11:45"], "m1": [58, 17, 98], "m2": [75, 13, 86], "m3": [57, 17, 89], "m4": [112, 21, 147], "position": [-33.46, -70.66], "pressure": 955.02, "temperature": 24.36, "unit": "001"}, {"altitude": 548.3, "date": ["2020-10-16 22:16:45", "2020-10-16 22:16:45", "2020-10-16 22:16:45"], "m1": [19, 10, 23], "m2": [24, 14, 28], "m3": [24, 16, 24], "m4": [27, 20, 30], "position": [-33.46, -70.66], "pressure": 955.03, "temperature": 23.86, "unit": "001"}]