[{"altitude": 545.7, "date": ["2020-10-14 10:41:46", "2020-10-14 10:41:46", "2020-10-14 10:41:46"], "m1": [6, 6, 6], "m2": [5, 5, 4], "m3": [6, 6, 6], "m4": [7, 9, 9], "position": [-33.46, -70.66], "pressure": 949.1853075770578, "temperature": 99.9, "unit": "002"}, {"altitude": 552.4, "date": ["2020-10-14 10:46:46", "2020-10-14 10:46:46", "2020-10-14 10:46:46"], "m1": [6, 6, 5], "m2": [4, 4, 4], "m3": [6, 6, 6], "m4": [9, 10, 9], "position": [-33.46, -70.66], "pressure": 948.4171962742852, "temperature": 99.9, "unit": "002"}, {"altitude": 544.2, "date": ["2020-10-14 10:51:46", "2020-10-14 10:51:46", "2020-10-14 10:51:46"], "m1": [6, 5, 5], "m2": [4, 4, 4], "m3": [6, 6, 6], "m4": [9, 9, 9], "position": [-33.46, -70.66], "pressure": 949.3573335820602, "temperature": 99.9, "unit": "002"}, {"altitude": 549.0, "date": ["2020-10-14 10:56:46", "2020-10-14 10:56:46", "2020-10-14 10:56:46"], "m1": [5, 6, 6], "m2": [4, 4, 4], "m3": [6, 6, 6], "m4": [9, 9, 9], "position": [-33.46, -70.66], "pressure": 948.8069286536654, "temperature": 99.9, "unit": "002"}, {"altitude": 552.8, "date": ["2020-10-14 11:01:46", "2020-10-14 11:01:46", "2020-10-14 11:01:46"], "m1": [6, 6, 6], "m2": [4, 4, 4], "m3": [6, 6, 6], "m4": [9, 9, 9], "position": [-33.46, -70.66], "pressure": 948.371352916594, "temperature": 99.9, "unit": "002"}, {"altitude": 544.0, "date": ["2020-10-14 11:06:46", "2020-10-14 11:06:46", "2020-10-14 11:06:46"], "m1": [6, 6, 7], "m2": [4, 4, 5], "m3": [6, 6, 6], "m4": [9, 8, 9], "position": [-33.46, -70.66], "pressure": 949.3802720632876, "temperature": 99.9, "unit": "002"}, {"altitude": 548.9, "date": ["2020-10-14 11:11:46", "2020-10-14 11:11:46", "2020-10-14 11:11:46"], "m1": [6, 5, 5], "m2": [4, 4, 4], "m3": [6, 6, 6], "m4": [9, 8, 9], "position": [-33.46, -70.66], "pressure": 948.8183931002069, "temperature": 99.9, "unit": "002"}, {"altitude": 550.4, "date": ["2020-10-14 11:16:46", "2020-10-14 11:16:46", "2020-10-14 11:16:46"], "m1": [6, 6, 6], "m2": [4, 4, 4], "m3": [6, 6, 7], "m4": [8, 8, 8], "position": [-33.46, -70.66], "pressure": 948.6464367794472, "temperature": 99.9, "unit": "002"}, {"altitude": 550.1, "date": ["2020-10-14 11:21:46", "2020-10-14 11:21:46", "2020-10-14 11:21:46"], "m1": [5, 5, 9], "m2": [4, 4, 4], "m3": [6, 6, 6], "m4": [8, 8, 8], "position": [-33.46, -70.66], "pressure": 948.6808262646565, "temperature": 99.9, "unit": "002"}, {"altitude": 548.3, "date": ["2020-10-14 11:26:46", "2020-10-14 11:26:46", "2020-10-14 11:26:46"], "m1": [6, 6, 6], "m2": [5, 5, 5], "m3": [5, 5, 5], "m4": [7, 7, 7], "position": [-33.46, -70.66], "pressure": 948.887181855003, "temperature": 99.9, "unit": "002"}, {"altitude": 546.2, "date": ["2020-10-14 11:31:46", "2020-10-14 11:31:46", "2020-10-14 11:31:46"], "m1": [6, 6, 6], "m2": [5, 5, 5], "m3": [5, 5, 5], "m4": [7, 7, 8], "position": [-33.46, -70.66], "pressure": 949.1279705180282, "temperature": 99.9, "unit": "002"}, {"altitude": 548.8, "date": ["2020-10-14 11:36:46", "2020-10-14 11:36:46", "2020-10-14 11:36:46"], "m1": [6, 6, 6], "m2": [5, 5, 5], "m3": [5, 5, 5], "m4": [7, 7, 7], "position": [-33.46, -70.66], "pressure": 948.8298576455832, "temperature": 99.9, "unit": "002"}, {"altitude": 551.6, "date": ["2020-10-14 11:41:46", "2020-10-14 11:41:46", "2020-10-14 11:41:46"], "m1": [6, 6, 6], "m2": [5, 4, 4], "m3": [5, 5, 5], "m4": [7, 7, 7], "position": [-33.46, -70.66], "pressure": 948.5088877329107, "temperature": 99.9, "unit": "002"}, {"altitude": 554.5, "date": ["2020-10-14 11:46:46", "2020-10-14 11:46:46", "2020-10-14 11:46:46"], "m1": [6, 6, 6], "m2": [4, 5, 4], "m3": [5, 5, 5], "m4": [7, 7, 7], "position": [-33.46, -70.66], "pressure": 948.1765362844646, "temperature": 99.9, "unit": "002"}, {"altitude": 551.5, "date": ["2020-10-14 11:51:46", "2020-10-14 11:51:46", "2020-10-14 11:51:46"], "m1": [6, 6, 6], "m2": [4, 4, 4], "m3": [5, 5, 5], "m4": [7, 7, 7], "position": [-33.46, -70.66], "pressure": 948.520349609928, "temperature": 99.9, "unit": "002"}, {"altitude": 551.7, "date": ["2020-10-14 11:56:46", "2020-10-14 11:56:46", "2020-10-14 11:56:46"], "m1": [6, 6, 6], "m2": [4, 4, 4], "m3": [5, 5, 5], "m4": [7, 7, 7], "position": [-33.46, -70.66], "pressure": 948.4974259547145, "temperature": 99.9, "unit": "002"}, {"altitude": 556.7, "date": ["2020-10-14 12:01:46", "2020-10-14 12:01:46", "2020-10-14 12:01:46"], "m1": [6, 6, 6], "m2": [5, 4, 4], "m3": [5, 5, 5], "m4": [7, 7, 7], "position": [-33.46, -70.66], "pressure": 947.9244630303746, "temperature": 99.9, "unit": "002"}, {"altitude": 553.7, "date": ["2020-10-14 12:06:46", "2020-10-14 12:06:46", "2020-10-14 12:06:46"], "m1": [6, 6, 6], "m2": [5, 4, 5], "m3": [5, 5, 6], "m4": [7, 7, 7], "position": [-33.46, -70.66], "pressure": 948.2682111424087, "temperature": 99.9, "unit": "002"}, {"altitude": 559.3, "date": ["2020-10-14 12:11:46", "2020-10-14 12:11:46", "2020-10-14 12:11:46"], "m1": [6, 6, 6], "m2": [4, 4, 4], "m3": [5, 5, 5], "m4": [7, 7, 7], "position": [-33.46, -70.66], "pressure": 947.6266199231782, "temperature": 99.9, "unit": "002"}, {"altitude": 562.1, "date": ["2020-10-14 12:16:46", "2020-10-14 12:16:46", "2020-10-14 12:16:46"], "m1": [6, 6, 6], "m2": [4, 4, 4], "m3": [5, 5, 5], "m4": [7, 7, 7], "position": [-33.46, -70.66], "pressure": 947.3059404864563, "temperature": 99.9, "unit": "002"}, {"altitude": 556.3, "date": ["2020-10-14 12:21:46", "2020-10-14 12:21:46", "2020-10-14 12:21:46"], "m1": [6, 6, 6], "m2": [4, 4, 4], "m3": [5, 5, 5], "m4": [7, 7, 7], "position": [-33.46, -70.66], "pressure": 947.9702909743401, "temperature": 99.9, "unit": "002"}, {"altitude": 554.5, "date": ["2020-10-14 12:26:46", "2020-10-14 12:26:46", "2020-10-14 12:26:46"], "m1": [6, 6, 6], "m2": [4, 4, 4], "m3": [5, 5, 5], "m4": [7, 7, 7], "position": [-33.46, -70.66], "pressure": 948.1765362844646, "temperature": 99.9, "unit": "002"}, {"altitude": 564.4, "date": ["2020-10-14 12:31:46", "2020-10-14 12:31:46", "2020-10-14 12:31:46"], "m1": [6, 6, 6], "m2": [4, 4, 4], "m3": [5, 5, 5], "m4": [7, 7, 7], "position": [-33.46, -70.66], "pressure": 947.042583162466, "temperature": 99.9, "unit": "002"}, {"altitude": 562.7, "date": ["2020-10-14 12:36:46", "2020-10-14 12:36:46", "2020-10-14 12:36:46"], "m1": [6, 6, 6], "m2": [4, 4, 4], "m3": [5, 5, 5], "m4": [7, 7, 8], "position": [-33.46, -70.66], "pressure": 947.2372335389621, "temperature": 99.9, "unit": "002"}, {"altitude": 571.3, "date": ["2020-10-14 12:41:46", "2020-10-14 12:41:46", "2020-10-14 12:41:46"], "m1": [6, 6, 6], "m2": [4, 4, 4], "m3": [5, 5, 5], "m4": [7, 7, 7], "position": [-33.46, -70.66], "pressure": 946.252824616334, "temperature": 99.9, "unit": "002"}, {"altitude": 0.0, "date": ["2020-10-14 13:15:26", "2020-10-14 13:15:26", "2020-10-14 13:15:26"], "m1": [15, 10, 9], "m2": [8, 6, 5], "m3": [11, 9, 7], "m4": [9, 9, 9], "position": [0.0, -70.66], "pressure": 0.0, "temperature": 99.9, "unit": "002"}, {"altitude": 557.8, "date": ["2020-10-14 13:25:32", "2020-10-14 13:25:32", "2020-10-14 13:25:32"], "m1": [503, 540, 607], "m2": [390, 416, 469], "m3": [480, 508, 573], "m4": [262, 252, 283], "position": [-33.46, -70.66], "pressure": 947.7984443349559, "temperature": 99.9, "unit": "002"}, {"altitude": 553.8, "date": ["2020-10-14 13:31:46", "2020-10-14 13:31:46", "2020-10-14 13:31:46"], "m1": [633, 631, 619], "m2": [490, 497, 468], "m3": [543, 589, 569], "m4": [325, 342, 287], "position": [-33.46, -70.66], "pressure": 948.2567514393351, "temperature": 99.9, "unit": "002"}, {"altitude": 556.4, "date": ["2020-10-14 13:36:46", "2020-10-14 13:36:46", "2020-10-14 13:36:46"], "m1": [632, 627, 644], "m2": [470, 469, 491], "m3": [576, 573, 583], "m4": [294, 248, 353], "position": [-33.46, -70.66], "pressure": 947.9588338401543, "temperature": 99.9, "unit": "002"}, {"altitude": 553.3, "date": ["2020-10-14 13:41:46", "2020-10-14 13:41:46", "2020-10-14 13:41:46"], "m1": [631, 642, 636], "m2": [487, 502, 498], "m3": [593, 580, 601], "m4": [327, 295, 325], "position": [-33.46, -70.66], "pressure": 948.3140509428107, "temperature": 99.9, "unit": "002"}, {"altitude": 568.6, "date": ["2020-10-14 13:46:46", "2020-10-14 13:46:46", "2020-10-14 13:46:46"], "m1": [676, 667, 684], "m2": [527, 519, 515], "m3": [629, 630, 631], "m4": [307, 337, 360], "position": [-33.46, -70.66], "pressure": 946.5618045853706, "temperature": 99.9, "unit": "002"}, {"altitude": 552.8, "date": ["2020-10-14 13:51:46", "2020-10-14 13:51:46", "2020-10-14 13:51:46"], "m1": [659, 659, 690], "m2": [513, 527, 542], "m3": [611, 622, 644], "m4": [314, 335, 348], "position": [-33.46, -70.66], "pressure": 948.371352916594, "temperature": 99.9, "unit": "002"}, {"altitude": 554.1, "date": ["2020-10-14 13:56:46", "2020-10-14 13:56:46", "2020-10-14 13:56:46"], "m1": [685, 674, 686], "m2": [525, 521, 555], "m3": [630, 639, 663], "m4": [311, 356, 343], "position": [-33.46, -70.66], "pressure": 948.2223729229706, "temperature": 99.9, "unit": "002"}, {"altitude": 544.9, "date": ["2020-10-14 14:01:46", "2020-10-14 14:01:46", "2020-10-14 14:01:46"], "m1": [737, 709, 724], "m2": [554, 560, 543], "m3": [673, 678, 689], "m4": [349, 369, 404], "position": [-33.46, -70.66], "pressure": 949.2770520117867, "temperature": 99.9, "unit": "002"}, {"altitude": 548.1, "date": ["2020-10-14 14:06:46", "2020-10-14 14:06:46", "2020-10-14 14:06:46"], "m1": [713, 719, 729], "m2": [566, 576, 579], "m3": [657, 692, 694], "m4": [357, 334, 364], "position": [-33.46, -70.66], "pressure": 948.9101122306321, "temperature": 99.9, "unit": "002"}, {"altitude": 543.8, "date": ["2020-10-14 14:11:46", "2020-10-14 14:11:46", "2020-10-14 14:11:46"], "m1": [755, 740, 751], "m2": [574, 585, 582], "m3": [704, 707, 689], "m4": [421, 359, 341], "position": [-33.46, -70.66], "pressure": 949.4032109399536, "temperature": 99.9, "unit": "002"}, {"altitude": 550.6, "date": ["2020-10-14 14:16:46", "2020-10-14 14:16:46", "2020-10-14 14:16:46"], "m1": [771, 745, 759], "m2": [564, 591, 598], "m3": [708, 710, 740], "m4": [360, 365, 396], "position": [-33.46, -70.66], "pressure": 948.6235109501105, "temperature": 99.9, "unit": "002"}, {"altitude": 560.4, "date": ["2020-10-14 14:21:46", "2020-10-14 14:21:46", "2020-10-14 14:21:46"], "m1": [767, 774, 792], "m2": [567, 596, 611], "m3": [721, 735, 712], "m4": [383, 365, 368], "position": [-33.46, -70.66], "pressure": 947.500629480424, "temperature": 99.9, "unit": "002"}, {"altitude": 563.2, "date": ["2020-10-14 14:26:46", "2020-10-14 14:26:46", "2020-10-14 14:26:46"], "m1": [784, 771, 787], "m2": [583, 593, 596], "m3": [745, 745, 755], "m4": [360, 423, 376], "position": [-33.46, -70.66], "pressure": 947.1799804654083, "temperature": 99.9, "unit": "002"}, {"altitude": 556.4, "date": ["2020-10-14 14:31:46", "2020-10-14 14:31:46", "2020-10-14 14:31:46"], "m1": [807, 792, 777], "m2": [639, 606, 616], "m3": [764, 739, 752], "m4": [374, 431, 428], "position": [-33.46, -70.66], "pressure": 947.9588338401543, "temperature": 99.9, "unit": "002"}, {"altitude": 556.5, "date": ["2020-10-14 14:36:46", "2020-10-14 14:36:46", "2020-10-14 14:36:46"], "m1": [825, 840, 752], "m2": [655, 647, 611], "m3": [785, 784, 771], "m4": [463, 388, 460], "position": [-33.46, -70.66], "pressure": 954.24, "temperature": 29.17, "unit": "002"}, {"altitude": 551.9, "date": ["2020-10-14 14:41:46", "2020-10-14 14:41:46", "2020-10-14 14:41:46"], "m1": [803, 816, 800], "m2": [623, 625, 656], "m3": [763, 755, 755], "m4": [390, 362, 391], "position": [-33.46, -70.66], "pressure": 954.18, "temperature": 29.66, "unit": "002"}, {"altitude": 553.6, "date": ["2020-10-14 14:46:46", "2020-10-14 14:46:46", "2020-10-14 14:46:46"], "m1": [792, 849, 825], "m2": [617, 612, 644], "m3": [772, 764, 755], "m4": [430, 387, 403], "position": [-33.46, -70.66], "pressure": 954.19, "temperature": 29.2, "unit": "002"}, {"altitude": 553.5, "date": ["2020-10-14 14:51:46", "2020-10-14 14:51:46", "2020-10-14 14:51:46"], "m1": [815, 827, 820], "m2": [619, 619, 608], "m3": [761, 760, 761], "m4": [402, 405, 389], "position": [-33.46, -70.66], "pressure": 948.291130844987, "temperature": 99.9, "unit": "002"}, {"altitude": 553.5, "date": ["2020-10-14 14:52:23", "2020-10-14 14:52:23", "2020-10-14 14:52:23"], "m1": [2925, 0, 0], "m2": [5, 0, 0], "m3": [2725, 0, 0], "m4": [8, 0, 0], "position": [-33.46, -70.66], "pressure": NaN, "temperature": NaN, "unit": "002"}, {"altitude": 554.1, "date": ["2020-10-14 14:56:46", "2020-10-14 14:56:46", "2020-10-14 14:56:46"], "m1": [880, 836, 875], "m2": [656, 652, 667], "m3": [816, 816, 803], "m4": [416, 420, 420], "position": [-33.46, -70.66], "pressure": NaN, "temperature": NaN, "unit": "002"}, {"altitude": 556.0, "date": ["2020-10-14 15:01:46", "2020-10-14 15:01:46", "2020-10-14 15:01:46"], "m1": [819, 835, 807], "m2": [627, 647, 611], "m3": [732, 774, 780], "m4": [381, 407, 421], "position": [-33.46, -70.66], "pressure": 948.0046629696812, "temperature": 99.9, "unit": "002"}, {"altitude": 556.5, "date": ["2020-10-14 15:06:46", "2020-10-14 15:06:46", "2020-10-14 15:06:46"], "m1": [885, 849, 864], "m2": [657, 651, 639], "m3": [790, 805, 787], "m4": [463, 452, 420], "position": [-33.46, -70.66], "pressure": 947.9473768047651, "temperature": 99.9, "unit": "002"}, {"altitude": 552.5, "date": ["2020-10-14 15:11:46", "2020-10-14 15:11:46", "2020-10-14 15:11:46"], "m1": [804, 812, 823], "m2": [620, 641, 632], "m3": [760, 775, 747], "m4": [395, 401, 404], "position": [-33.46, -70.66], "pressure": NaN, "temperature": NaN, "unit": "002"}, {"altitude": 556.6, "date": ["2020-10-14 15:16:46", "2020-10-14 15:16:46", "2020-10-14 15:16:46"], "m1": [859, 888, 864], "m2": [692, 673, 647], "m3": [829, 827, 790], "m4": [466, 437, 427], "position": [-33.46, -70.66], "pressure": 954.24, "temperature": 29.53, "unit": "002"}, {"altitude": 555.0, "date": ["2020-10-14 15:21:46", "2020-10-14 15:21:46", "2020-10-14 15:21:46"], "m1": [878, 867, 899], "m2": [662, 654, 654], "m3": [803, 803, 812], "m4": [433, 438, 432], "position": [-33.46, -70.66], "pressure": 954.33, "temperature": 29.74, "unit": "002"}, {"altitude": 552.9, "date": ["2020-10-14 15:26:46", "2020-10-14 15:26:46", "2020-10-14 15:26:46"], "m1": [864, 883, 824], "m2": [664, 671, 616], "m3": [831, 799, 824], "m4": [413, 448, 428], "position": [-33.46, -70.66], "pressure": 954.4, "temperature": 30.44, "unit": "002"}, {"altitude": 567.2, "date": ["2020-10-14 15:31:46", "2020-10-14 15:31:46", "2020-10-14 15:31:46"], "m1": [876, 867, 888], "m2": [672, 667, 696], "m3": [819, 807, 794], "m4": [448, 487, 403], "position": [-33.46, -70.66], "pressure": 946.7220447572797, "temperature": 99.9, "unit": "002"}, {"altitude": 554.0, "date": ["2020-10-14 15:36:46", "2020-10-14 15:36:46", "2020-10-14 15:36:46"], "m1": [907, 887, 864], "m2": [668, 665, 672], "m3": [840, 816, 828], "m4": [464, 417, 455], "position": [-33.46, -70.66], "pressure": NaN, "temperature": NaN, "unit": "002"}, {"altitude": 551.2, "date": ["2020-10-14 15:41:46", "2020-10-14 15:41:46", "2020-10-14 15:41:46"], "m1": [907, 924, 894], "m2": [700, 676, 691], "m3": [846, 862, 832], "m4": [459, 444, 449], "position": [-33.46, -70.66], "pressure": 954.36, "temperature": 30.28, "unit": "002"}, {"altitude": 551.2, "date": ["2020-10-14 15:42:23", "2020-10-14 15:42:23", "2020-10-14 15:42:23"], "m1": [77, 0, 0], "m2": [5, 0, 0], "m3": [1045, 0, 0], "m4": [8, 0, 0], "position": [-33.46, -70.66], "pressure": 954.35, "temperature": 30.17, "unit": "002"}, {"altitude": 554.2, "date": ["2020-10-14 15:46:46", "2020-10-14 15:46:46", "2020-10-14 15:46:46"], "m1": [918, 891, 918], "m2": [699, 688, 700], "m3": [847, 823, 824], "m4": [455, 505, 476], "position": [-33.46, -70.66], "pressure": 954.33, "temperature": 31.45, "unit": "002"}, {"altitude": 555.9, "date": ["2020-10-14 15:51:46", "2020-10-14 15:51:46", "2020-10-14 15:51:46"], "m1": [918, 889, 937], "m2": [719, 707, 684], "m3": [846, 844, 860], "m4": [460, 507, 454], "position": [-33.46, -70.66], "pressure": 954.24, "temperature": 32.11, "unit": "002"}, {"altitude": 557.6, "date": ["2020-10-14 15:56:46", "2020-10-14 15:56:46", "2020-10-14 15:56:46"], "m1": [908, 920, 921], "m2": [739, 716, 679], "m3": [872, 870, 854], "m4": [498, 457, 523], "position": [-33.46, -70.66], "pressure": NaN, "temperature": NaN, "unit": "002"}, {"altitude": 549.8, "date": ["2020-10-14 16:01:46", "2020-10-14 16:01:46", "2020-10-14 16:01:46"], "m1": [936, 903, 913], "m2": [683, 707, 697], "m3": [856, 856, 849], "m4": [436, 473, 480], "position": [-33.46, -70.66], "pressure": NaN, "temperature": NaN, "unit": "002"}, {"altitude": 555.0, "date": ["2020-10-14 16:06:46", "2020-10-14 16:06:46", "2020-10-14 16:06:46"], "m1": [943, 928, 939], "m2": [700, 729, 724], "m3": [856, 850, 860], "m4": [427, 440, 496], "position": [-33.46, -70.66], "pressure": 954.19, "temperature": 30.99, "unit": "002"}, {"altitude": 558.7, "date": ["2020-10-14 16:11:46", "2020-10-14 16:11:46", "2020-10-14 16:11:46"], "m1": [903, 888, 895], "m2": [711, 716, 702], "m3": [851, 851, 838], "m4": [456, 526, 496], "position": [-33.46, -70.66], "pressure": 954.18, "temperature": 31.96, "unit": "002"}, {"altitude": 552.6, "date": ["2020-10-14 16:16:46", "2020-10-14 16:16:46", "2020-10-14 16:16:46"], "m1": [935, 936, 940], "m2": [718, 720, 716], "m3": [849, 867, 871], "m4": [456, 524, 497], "position": [-33.46, -70.66], "pressure": NaN, "temperature": NaN, "unit": "002"}, {"altitude": 553.4, "date": ["2020-10-14 16:21:46", "2020-10-14 16:21:46", "2020-10-14 16:21:46"], "m1": [886, 787, 780], "m2": [656, 624, 630], "m3": [816, 750, 738], "m4": [448, 395, 401], "position": [-33.46, -70.66], "pressure": 954.09, "temperature": 29.74, "unit": "002"}, {"altitude": 557.1, "date": ["2020-10-14 16:26:46", "2020-10-14 16:26:46", "2020-10-14 16:26:46"], "m1": [384, 288, 283], "m2": [329, 194, 222], "m3": [391, 276, 200], "m4": [198, 211, 233], "position": [-33.46, -70.66], "pressure": NaN, "temperature": NaN, "unit": "002"}, {"altitude": 556.6, "date": ["2020-10-14 16:31:46", "2020-10-14 16:31:46", "2020-10-14 16:31:46"], "m1": [793, 915, 916], "m2": [588, 662, 683], "m3": [720, 820, 839], "m4": [409, 440, 419], "position": [-33.46, -70.66], "pressure": 953.98, "temperature": 30.18, "unit": "002"}, {"altitude": 555.7, "date": ["2020-10-14 16:36:46", "2020-10-14 16:36:46", "2020-10-14 16:36:46"], "m1": [964, 935, 929], "m2": [755, 726, 732], "m3": [857, 859, 856], "m4": [497, 460, 472], "position": [-33.46, -70.66], "pressure": 953.96, "temperature": 31.78, "unit": "002"}, {"altitude": 548.0, "date": ["2020-10-14 16:41:46", "2020-10-14 16:41:46", "2020-10-14 16:41:46"], "m1": [904, 960, 972], "m2": [744, 739, 731], "m3": [889, 864, 889], "m4": [463, 452, 462], "position": [-33.46, -70.66], "pressure": 953.85, "temperature": 33.37, "unit": "002"}, {"altitude": 550.0, "date": ["2020-10-14 16:46:46", "2020-10-14 16:46:46", "2020-10-14 16:46:46"], "m1": [947, 971, 947], "m2": [719, 740, 727], "m3": [891, 880, 903], "m4": [490, 516, 500], "position": [-33.46, -70.66], "pressure": 953.81, "temperature": 32.96, "unit": "002"}, {"altitude": 551.6, "date": ["2020-10-14 16:51:46", "2020-10-14 16:51:46", "2020-10-14 16:51:46"], "m1": [979, 947, 935], "m2": [742, 748, 721], "m3": [889, 844, 881], "m4": [536, 507, 488], "position": [-33.46, -70.66], "pressure": 953.84, "temperature": 32.14, "unit": "002"}, {"altitude": 557.2, "date": ["2020-10-14 16:56:46", "2020-10-14 16:56:46", "2020-10-14 16:56:46"], "m1": [963, 935, 961], "m2": [758, 710, 723], "m3": [883, 888, 894], "m4": [473, 492, 480], "position": [-33.46, -70.66], "pressure": 953.83, "temperature": 33.14, "unit": "002"}, {"altitude": 557.2, "date": ["2020-10-14 16:57:23", "2020-10-14 16:57:23", "2020-10-14 16:57:23"], "m1": [7, 0, 0], "m2": [6, 0, 0], "m3": [2389, 0, 0], "m4": [7, 0, 0], "position": [-33.46, -70.66], "pressure": 953.81, "temperature": 33.16, "unit": "002"}, {"altitude": 556.9, "date": ["2020-10-14 17:01:46", "2020-10-14 17:01:46", "2020-10-14 17:01:46"], "m1": [908, 964, 927], "m2": [753, 719, 711], "m3": [864, 860, 863], "m4": [480, 457, 463], "position": [-33.46, -70.66], "pressure": 953.86, "temperature": 33.6, "unit": "002"}, {"altitude": 554.0, "date": ["2020-10-14 17:06:46", "2020-10-14 17:06:46", "2020-10-14 17:06:46"], "m1": [915, 958, 929], "m2": [716, 707, 720], "m3": [860, 871, 867], "m4": [438, 476, 454], "position": [-33.46, -70.66], "pressure": 953.81, "temperature": 32.85, "unit": "002"}, {"altitude": 552.9, "date": ["2020-10-14 17:11:46", "2020-10-14 17:11:46", "2020-10-14 17:11:46"], "m1": [944, 947, 960], "m2": [711, 699, 734], "m3": [867, 851, 831], "m4": [416, 477, 487], "position": [-33.46, -70.66], "pressure": NaN, "temperature": NaN, "unit": "002"}, {"altitude": 559.8, "date": ["2020-10-14 17:16:46", "2020-10-14 17:16:46", "2020-10-14 17:16:46"], "m1": [918, 916, 892], "m2": [716, 725, 660], "m3": [854, 851, 832], "m4": [466, 425, 480], "position": [-33.46, -70.66], "pressure": NaN, "temperature": NaN, "unit": "002"}, {"altitude": 550.7, "date": ["2020-10-14 17:21:46", "2020-10-14 17:21:46", "2020-10-14 17:21:46"], "m1": [932, 920, 915], "m2": [686, 667, 700], "m3": [855, 847, 871], "m4": [467, 468, 519], "position": [-33.46, -70.66], "pressure": 953.69, "temperature": 32.78, "unit": "002"}, {"altitude": 561.8, "date": ["2020-10-14 17:26:46", "2020-10-14 17:26:46", "2020-10-14 17:26:46"], "m1": [920, 880, 932], "m2": [696, 696, 697], "m3": [860, 871, 865], "m4": [495, 449, 443], "position": [-33.46, -70.66], "pressure": 953.69, "temperature": 31.64, "unit": "002"}, {"altitude": 551.9, "date": ["2020-10-14 17:31:46", "2020-10-14 17:31:46", "2020-10-14 17:31:46"], "m1": [931, 927, 911], "m2": [697, 718, 742], "m3": [856, 847, 856], "m4": [438, 464, 493], "position": [-33.46, -70.66], "pressure": 953.65, "temperature": 32.31, "unit": "002"}, {"altitude": 553.2, "date": ["2020-10-14 17:36:46", "2020-10-14 17:36:46", "2020-10-14 17:36:46"], "m1": [920, 920, 904], "m2": [679, 711, 691], "m3": [843, 835, 847], "m4": [503, 496, 426], "position": [-33.46, -70.66], "pressure": 953.67, "temperature": 32.09, "unit": "002"}, {"altitude": 547.6, "date": ["2020-10-14 17:41:46", "2020-10-14 17:41:46", "2020-10-14 17:41:46"], "m1": [844, 911, 895], "m2": [713, 704, 692], "m3": [832, 817, 825], "m4": [452, 419, 415], "position": [-33.46, -70.66], "pressure": NaN, "temperature": NaN, "unit": "002"}, {"altitude": 548.8, "date": ["2020-10-14 17:46:46", "2020-10-14 17:46:46", "2020-10-14 17:46:46"], "m1": [848, 937, 889], "m2": [660, 688, 718], "m3": [809, 817, 812], "m4": [409, 440, 487], "position": [-33.46, -70.66], "pressure": NaN, "temperature": NaN, "unit": "002"}, {"altitude": 548.4, "date": ["2020-10-14 17:51:46", "2020-10-14 17:51:46", "2020-10-14 17:51:46"], "m1": [911, 878, 888], "m2": [676, 708, 684], "m3": [839, 806, 835], "m4": [508, 441, 423], "position": [-33.46, -70.66], "pressure": NaN, "temperature": NaN, "unit": "002"}, {"altitude": 546.6, "date": ["2020-10-14 17:56:46", "2020-10-14 17:56:46", "2020-10-14 17:56:46"], "m1": [937, 908, 884], "m2": [708, 703, 716], "m3": [835, 836, 852], "m4": [430, 460, 446], "position": [-33.46, -70.66], "pressure": NaN, "temperature": NaN, "unit": "002"}, {"altitude": 547.0, "date": ["2020-10-14 18:01:46", "2020-10-14 18:01:46", "2020-10-14 18:01:46"], "m1": [872, 880, 888], "m2": [681, 703, 716], "m3": [830, 828, 821], "m4": [460, 460, 439], "position": [-33.46, -70.66], "pressure": 949.0362363636765, "temperature": NaN, "unit": "002"}, {"altitude": 546.5, "date": ["2020-10-14 18:06:46", "2020-10-14 18:06:46", "2020-10-14 18:06:46"], "m1": [897, 879, 847], "m2": [659, 684, 657], "m3": [817, 814, 819], "m4": [428, 423, 421], "position": [-33.46, -70.66], "pressure": NaN, "temperature": NaN, "unit": "002"}, {"altitude": 548.5, "date": ["2020-10-14 18:31:46", "2020-10-14 18:31:46", "2020-10-14 18:31:46"], "m1": [824, 854, 835], "m2": [603, 632, 634], "m3": [780, 750, 779], "m4": [393, 418, 434], "position": [-33.46, -70.66], "pressure": NaN, "temperature": NaN, "unit": "002"}, {"altitude": 548.5, "date": ["2020-10-14 18:32:23", "2020-10-14 18:32:23", "2020-10-14 18:32:23"], "m1": [1349, 0, 0], "m2": [5, 0, 0], "m3": [2725, 0, 0], "m4": [7, 0, 0], "position": [-33.46, -70.66], "pressure": 953.22, "temperature": 31.4, "unit": "002"}, {"altitude": 551.5, "date": ["2020-10-14 18:36:46", "2020-10-14 18:36:46", "2020-10-14 18:36:46"], "m1": [791, 843, 836], "m2": [624, 656, 667], "m3": [780, 783, 785], "m4": [406, 431, 440], "position": [-33.46, -70.66], "pressure": NaN, "temperature": NaN, "unit": "002"}, {"altitude": 541.4, "date": ["2020-10-14 18:41:46", "2020-10-14 18:41:46", "2020-10-14 18:41:46"], "m1": [803, 823, 824], "m2": [657, 623, 608], "m3": [739, 761, 760], "m4": [375, 395, 444], "position": [-33.46, -70.66], "pressure": 953.04, "temperature": 33.15, "unit": "002"}, {"altitude": 545.6, "date": ["2020-10-14 18:46:46", "2020-10-14 18:46:46", "2020-10-14 18:46:46"], "m1": [828, 809, 852], "m2": [619, 631, 619], "m3": [750, 747, 760], "m4": [406, 408, 372], "position": [-33.46, -70.66], "pressure": 953.01, "temperature": 33.8, "unit": "002"}, {"altitude": 542.9, "date": ["2020-10-14 18:51:46", "2020-10-14 18:51:46", "2020-10-14 18:51:46"], "m1": [787, 815, 814], "m2": [579, 595, 641], "m3": [736, 750, 752], "m4": [433, 451, 406], "position": [-33.46, -70.66], "pressure": 953.03, "temperature": 33.92, "unit": "002"}, {"altitude": 538.4, "date": ["2020-10-14 18:56:46", "2020-10-14 18:56:46", "2020-10-14 18:56:46"], "m1": [787, 822, 755], "m2": [611, 593, 574], "m3": [732, 729, 718], "m4": [368, 368, 355], "position": [-33.46, -70.66], "pressure": 952.9, "temperature": 32.07, "unit": "002"}, {"altitude": 537.7, "date": ["2020-10-14 19:01:46", "2020-10-14 19:01:46", "2020-10-14 19:01:46"], "m1": [755, 765, 736], "m2": [583, 616, 554], "m3": [711, 715, 702], "m4": [351, 341, 352], "position": [-33.46, -70.66], "pressure": 950.1030366584658, "temperature": 99.9, "unit": "002"}, {"altitude": 540.1, "date": ["2020-10-14 19:06:46", "2020-10-14 19:06:46", "2020-10-14 19:06:46"], "m1": [747, 752, 784], "m2": [608, 595, 580], "m3": [691, 698, 723], "m4": [391, 398, 390], "position": [-33.46, -70.66], "pressure": 949.8276514905992, "temperature": 99.9, "unit": "002"}, {"altitude": 540.1, "date": ["2020-10-14 19:07:23", "2020-10-14 19:07:23", "2020-10-14 19:07:23"], "m1": [2733, 0, 0], "m2": [5, 0, 0], "m3": [2565, 0, 0], "m4": [7, 0, 0], "position": [-33.46, -70.66], "pressure": 949.8276514905992, "temperature": 99.9, "unit": "002"}, {"altitude": 538.2, "date": ["2020-10-14 19:31:46", "2020-10-14 19:31:46", "2020-10-14 19:31:46"], "m1": [675, 671, 684], "m2": [531, 527, 509], "m3": [640, 635, 622], "m4": [388, 357, 324], "position": [-33.46, -70.66], "pressure": 950.045660051365, "temperature": 99.9, "unit": "002"}, {"altitude": 541.0, "date": ["2020-10-14 19:36:46", "2020-10-14 19:36:46", "2020-10-14 19:36:46"], "m1": [675, 675, 675], "m2": [547, 523, 524], "m3": [648, 636, 633], "m4": [324, 335, 335], "position": [-33.46, -70.66], "pressure": 949.7243967366506, "temperature": 99.9, "unit": "002"}, {"altitude": 546.9, "date": ["2020-10-14 19:41:46", "2020-10-14 19:41:46", "2020-10-14 19:41:46"], "m1": [627, 630, 641], "m2": [495, 487, 502], "m3": [591, 603, 608], "m4": [359, 312, 311], "position": [-33.46, -70.66], "pressure": 949.0477027870096, "temperature": 99.9, "unit": "002"}, {"altitude": 545.7, "date": ["2020-10-14 19:46:46", "2020-10-14 19:46:46", "2020-10-14 19:46:46"], "m1": [643, 628, 634], "m2": [480, 481, 503], "m3": [599, 572, 580], "m4": [358, 264, 263], "position": [-33.46, -70.66], "pressure": 949.1853075770578, "temperature": 99.9, "unit": "002"}, {"altitude": 544.9, "date": ["2020-10-14 19:51:46", "2020-10-14 19:51:46", "2020-10-14 19:51:46"], "m1": [619, 617, 625], "m2": [475, 472, 488], "m3": [580, 579, 556], "m4": [320, 310, 276], "position": [-33.46, -70.66], "pressure": 949.2770520117867, "temperature": 99.9, "unit": "002"}, {"altitude": 556.6, "date": ["2020-10-14 19:56:46", "2020-10-14 19:56:46", "2020-10-14 19:56:46"], "m1": [595, 567, 592], "m2": [463, 455, 448], "m3": [536, 527, 535], "m4": [255, 276, 222], "position": [-33.46, -70.66], "pressure": 947.9359198681723, "temperature": 99.9, "unit": "002"}, {"altitude": 551.1, "date": ["2020-10-14 20:01:46", "2020-10-14 20:01:46", "2020-10-14 20:01:46"], "m1": [579, 584, 540], "m2": [438, 464, 443], "m3": [548, 523, 491], "m4": [301, 244, 241], "position": [-33.46, -70.66], "pressure": 948.5661981062166, "temperature": 99.9, "unit": "002"}, {"altitude": 553.3, "date": ["2020-10-14 20:06:46", "2020-10-14 20:06:46", "2020-10-14 20:06:46"], "m1": [544, 547, 549], "m2": [434, 433, 435], "m3": [526, 521, 523], "m4": [243, 226, 229], "position": [-33.46, -70.66], "pressure": 948.3140509428107, "temperature": 99.9, "unit": "002"}, {"altitude": 544.6, "date": ["2020-10-14 20:11:46", "2020-10-14 20:11:46", "2020-10-14 20:11:46"], "m1": [536, 523, 516], "m2": [412, 410, 407], "m3": [503, 499, 510], "m4": [277, 247, 247], "position": [-33.46, -70.66], "pressure": 949.3114578059055, "temperature": 99.9, "unit": "002"}, {"altitude": 548.6, "date": ["2020-10-14 20:16:46", "2020-10-14 20:16:46", "2020-10-14 20:16:46"], "m1": [514, 509, 510], "m2": [384, 398, 403], "m3": [489, 487, 467], "m4": [227, 279, 235], "position": [-33.46, -70.66], "pressure": 948.8527870328419, "temperature": 99.9, "unit": "002"}, {"altitude": 547.5, "date": ["2020-10-14 20:21:46", "2020-10-14 20:21:46", "2020-10-14 20:21:46"], "m1": [501, 486, 508], "m2": [384, 372, 397], "m3": [476, 479, 472], "m4": [229, 233, 203], "position": [-33.46, -70.66], "pressure": 948.9789057296668, "temperature": 99.9, "unit": "002"}, {"altitude": 549.5, "date": ["2020-10-14 20:26:46", "2020-10-14 20:26:46", "2020-10-14 20:26:46"], "m1": [434, 482, 484], "m2": [347, 387, 375], "m3": [437, 466, 459], "m4": [185, 201, 210], "position": [-33.46, -70.66], "pressure": 948.7496079034615, "temperature": 99.9, "unit": "002"}, {"altitude": 549.1, "date": ["2020-10-14 20:31:46", "2020-10-14 20:31:46", "2020-10-14 20:31:46"], "m1": [496, 470, 471], "m2": [371, 382, 368], "m3": [454, 454, 452], "m4": [198, 227, 203], "position": [-33.46, -70.66], "pressure": 948.7954643059581, "temperature": 99.9, "unit": "002"}, {"altitude": 544.6, "date": ["2020-10-14 20:36:46", "2020-10-14 20:36:46", "2020-10-14 20:36:46"], "m1": [443, 430, 443], "m2": [345, 347, 344], "m3": [423, 428, 409], "m4": [227, 196, 207], "position": [-33.46, -70.66], "pressure": 949.3114578059055, "temperature": 99.9, "unit": "002"}, {"altitude": 564.8, "date": ["2020-10-14 20:41:46", "2020-10-14 20:41:46", "2020-10-14 20:41:46"], "m1": [424, 431, 421], "m2": [348, 343, 335], "m3": [409, 417, 409], "m4": [189, 218, 196], "position": [-33.46, -70.66], "pressure": 946.9967872217119, "temperature": 99.9, "unit": "002"}, {"altitude": 548.6, "date": ["2020-10-14 20:46:46", "2020-10-14 20:46:46", "2020-10-14 20:46:46"], "m1": [406, 391, 404], "m2": [310, 312, 319], "m3": [371, 372, 382], "m4": [212, 187, 236], "position": [-33.46, -70.66], "pressure": 948.8527870328419, "temperature": 99.9, "unit": "002"}, {"altitude": 549.5, "date": ["2020-10-14 20:51:46", "2020-10-14 20:51:46", "2020-10-14 20:51:46"], "m1": [369, 353, 364], "m2": [287, 283, 287], "m3": [356, 353, 348], "m4": [206, 202, 250], "position": [-33.46, -70.66], "pressure": 948.7496079034615, "temperature": 99.9, "unit": "002"}, {"altitude": 549.5, "date": ["2020-10-14 20:56:46", "2020-10-14 20:56:46", "2020-10-14 20:56:46"], "m1": [350, 368, 339], "m2": [270, 290, 268], "m3": [338, 337, 319], "m4": [178, 195, 194], "position": [-33.46, -70.66], "pressure": 948.7496079034615, "temperature": 99.9, "unit": "002"}, {"altitude": 552.0, "date": ["2020-10-14 21:01:46", "2020-10-14 21:01:46", "2020-10-14 21:01:46"], "m1": [329, 327, 328], "m2": [253, 243, 264], "m3": [307, 307, 306], "m4": [194, 208, 188], "position": [-33.46, -70.66], "pressure": 948.4630412130463, "temperature": 99.9, "unit": "002"}, {"altitude": 548.3, "date": ["2020-10-14 21:06:46", "2020-10-14 21:06:46", "2020-10-14 21:06:46"], "m1": [318, 309, 297], "m2": [250, 241, 240], "m3": [289, 288, 283], "m4": [192, 212, 163], "position": [-33.46, -70.66], "pressure": 948.887181855003, "temperature": 99.9, "unit": "002"}, {"altitude": 544.4, "date": ["2020-10-14 21:11:46", "2020-10-14 21:11:46", "2020-10-14 21:11:46"], "m1": [279, 281, 236], "m2": [212, 228, 183], "m3": [260, 263, 216], "m4": [196, 166, 178], "position": [-33.46, -70.66], "pressure": 949.3343954962675, "temperature": 99.9, "unit": "002"}, {"altitude": 541.9, "date": ["2020-10-14 21:16:46", "2020-10-14 21:16:46", "2020-10-14 21:16:46"], "m1": [263, 255, 233], "m2": [219, 197, 190], "m3": [240, 231, 216], "m4": [188, 177, 188], "position": [-33.46, -70.66], "pressure": 949.6211499915785, "temperature": 99.9, "unit": "002"}, {"altitude": 546.6, "date": ["2020-10-14 21:21:46", "2020-10-14 21:21:46", "2020-10-14 21:21:46"], "m1": [235, 243, 221], "m2": [203, 182, 191], "m3": [214, 220, 216], "m4": [192, 202, 191], "position": [-33.46, -70.66], "pressure": 949.0821026500804, "temperature": 99.9, "unit": "002"}, {"altitude": 546.6, "date": ["2020-10-14 21:22:23", "2020-10-14 21:22:23", "2020-10-14 21:22:23"], "m1": [6, 0, 0], "m2": [5, 0, 0], "m3": [1093, 0, 0], "m4": [7, 0, 0], "position": [-33.46, -70.66], "pressure": 949.0821026500804, "temperature": 99.9, "unit": "002"}, {"altitude": 543.4, "date": ["2020-10-14 21:26:46", "2020-10-14 21:26:46", "2020-10-14 21:26:46"], "m1": [216, 225, 223], "m2": [185, 183, 175], "m3": [204, 202, 200], "m4": [148, 174, 148], "position": [-33.46, -70.66], "pressure": 949.4490898796195, "temperature": 99.9, "unit": "002"}, {"altitude": 545.9, "date": ["2020-10-14 21:31:46", "2020-10-14 21:31:46", "2020-10-14 21:31:46"], "m1": [185, 184, 172], "m2": [174, 150, 145], "m3": [172, 163, 161], "m4": [115, 110, 79], "position": [-33.46, -70.66], "pressure": 949.1623724568962, "temperature": 99.9, "unit": "002"}, {"altitude": 546.4, "date": ["2020-10-14 21:36:46", "2020-10-14 21:36:46", "2020-10-14 21:36:46"], "m1": [152, 155, 120], "m2": [116, 121, 124], "m3": [128, 145, 125], "m4": [57, 66, 65], "position": [-33.46, -70.66], "pressure": 949.1050363863593, "temperature": 99.9, "unit": "002"}, {"altitude": 545.2, "date": ["2020-10-14 21:41:46", "2020-10-14 21:41:46", "2020-10-14 21:41:46"], "m1": [135, 138, 135], "m2": [113, 119, 120], "m3": [122, 131, 119], "m4": [63, 56, 57], "position": [-33.46, -70.66], "pressure": 949.2426471073636, "temperature": 99.9, "unit": "002"}, {"altitude": 548.5, "date": ["2020-10-14 21:46:46", "2020-10-14 21:46:46", "2020-10-14 21:46:46"], "m1": [115, 112, 114], "m2": [112, 98, 104], "m3": [97, 101, 96], "m4": [37, 64, 53], "position": [-33.46, -70.66], "pressure": 948.8642518747255, "temperature": 99.9, "unit": "002"}, {"altitude": 546.1, "date": ["2020-10-14 21:51:46", "2020-10-14 21:51:46", "2020-10-14 21:51:46"], "m1": [88, 102, 90], "m2": [89, 103, 80], "m3": [82, 85, 78], "m4": [57, 47, 43], "position": [-33.46, -70.66], "pressure": 949.1394377321348, "temperature": 99.9, "unit": "002"}, {"altitude": 554.3, "date": ["2020-10-14 21:56:46", "2020-10-14 21:56:46", "2020-10-14 21:56:46"], "m1": [80, 74, 76], "m2": [67, 97, 97], "m3": [71, 77, 75], "m4": [60, 60, 38], "position": [-33.46, -70.66], "pressure": 948.1994544061031, "temperature": 99.9, "unit": "002"}, {"altitude": 568.7, "date": ["2020-10-14 22:01:46", "2020-10-14 22:01:46", "2020-10-14 22:01:46"], "m1": [60, 64, 41], "m2": [38, 32, 35], "m3": [65, 66, 59], "m4": [34, 32, 34], "position": [-33.46, -70.66], "pressure": 946.5503595993295, "temperature": 99.9, "unit": "002"}, {"altitude": 549.9, "date": ["2020-10-14 22:06:46", "2020-10-14 22:06:46", "2020-10-14 22:06:46"], "m1": [41, 42, 44], "m2": [27, 29, 27], "m3": [48, 39, 34], "m4": [25, 34, 20], "position": [-33.46, -70.66], "pressure": 948.7037530822718, "temperature": 99.9, "unit": "002"}, {"altitude": 551.0, "date": ["2020-10-14 22:11:46", "2020-10-14 22:11:46", "2020-10-14 22:11:46"], "m1": [20, 19, 22], "m2": [12, 15, 18], "m3": [12, 16, 22], "m4": [8, 9, 12], "position": [-33.46, -70.66], "pressure": 948.5776604773463, "temperature": 99.9, "unit": "002"}, {"altitude": 547.4, "date": ["2020-10-14 22:16:46", "2020-10-14 22:16:46", "2020-10-14 22:16:46"], "m1": [15, 18, 17], "m2": [11, 9, 9], "m3": [10, 17, 16], "m4": [8, 9, 8], "position": [-33.46, -70.66], "pressure": 948.990371658783, "temperature": 99.9, "unit": "002"}]